FortranIO.py
MANIFEST.in
Makefile
README.txt
psls.py
psls.yaml
setup.py
sls.py
spotintime.py
transit.py
universal_pattern.py
doc/PSLS_v1.2_release_note.pdf
doc/PSLS_v1.3_release_note.pdf
examples/0009882316.yaml
examples/0012069449.yaml
models/0012069449.gsm
models/modeprop.txt
psls.egg-info/PKG-INFO
psls.egg-info/SOURCES.txt
psls.egg-info/dependency_links.txt
psls.egg-info/requires.txt
psls.egg-info/top_level.txt
systematics/PLATO_systematics_BOL_FixedMask_V2.npy
systematics/PLATO_systematics_BOL_P1_V2.npy
systematics/PLATO_systematics_BOL_V2.npy
systematics/PLATO_systematics_EOL_FixedMask_V2.npy
systematics/PLATO_systematics_EOL_P1_V2.npy
systematics/PLATO_systematics_EOL_V2.npy