Metadata-Version: 2.1
Name: psls
Version: 1.8
Summary: PLATO Stellar Light-curve Simulator (SLS): Simulate stochastically-excited oscillations together with other stellar and instrumental components
Home-page: https://sites.lesia.obspm.fr/psls/
Author: R. Samadi
Author-email: reza.samadi@obspm.fr
Requires-Python: >=3.5
Requires-Dist: numpy
Requires-Dist: scipy
Requires-Dist: pyyaml
Requires-Dist: h5py
Requires-Dist: packaging
Requires-Dist: astropy
Requires-Dist: matplotlib
